aixblock_crawler/__init__.py
aixblock_crawler/builtin/__init__.py
aixblock_crawler/builtin/baidu.py
aixblock_crawler/builtin/bing.py
aixblock_crawler/builtin/filter.py
aixblock_crawler/builtin/flickr.py
aixblock_crawler/builtin/google.py
aixblock_crawler/builtin/google_document.py
aixblock_crawler/builtin/greedy.py
aixblock_crawler/builtin/pinterest.py
aixblock_crawler/builtin/urllist.py
aixblock_crawler/builtin/yandex.py
aixblock_crawler/crawler.py
aixblock_crawler/downloader.py
aixblock_crawler/feeder.py
aixblock_crawler/parser.py
aixblock_crawler/storage/__init__.py
aixblock_crawler/storage/base.py
aixblock_crawler/storage/filesystem.py
aixblock_crawler/storage/google_storage.py
aixblock_crawler/utils/__init__.py
aixblock_crawler/utils/cached_queue.py
aixblock_crawler/utils/proxy_pool.py
aixblock_crawler/utils/session.py
aixblock_crawler/utils/signal.py
aixblock_crawler/utils/thread_pool.py
aixblock_crawler/version.py
aixblock_crawler-0.0.2.dist-info/METADATA
aixblock_crawler-0.0.2.dist-info/WHEEL
aixblock_crawler-0.0.2.dist-info/RECORD
